simple_mysql_mcp_server/__init__.py
simple_mysql_mcp_server/database.py
simple_mysql_mcp_server/main.py
simple_mysql_mcp_server-0.1.4.dist-info/licenses/LICENSE
simple_mysql_mcp_server-0.1.4.dist-info/METADATA
simple_mysql_mcp_server-0.1.4.dist-info/WHEEL
simple_mysql_mcp_server-0.1.4.dist-info/entry_points.txt
simple_mysql_mcp_server-0.1.4.dist-info/top_level.txt
simple_mysql_mcp_server-0.1.4.dist-info/RECORD
