Metadata-Version: 2.4
Name: simple-mysql-mcp-server
Version: 0.1.4
Summary: A MySQL-compatible MCP server for GitHub Copilot and LLMs.
Author: Rehan Tariq
License: MIT
Classifier: Programming Language :: Python :: 3
Classifier: License :: OSI Approved :: MIT License
License-File: LICENSE
Requires-Dist: fastapi
Requires-Dist: uvicorn[standard]
Requires-Dist: sqlalchemy
Requires-Dist: pymysql
Requires-Dist: cryptography
Dynamic: author
Dynamic: classifier
Dynamic: description
Dynamic: description-content-type
Dynamic: license
Dynamic: license-file
Dynamic: requires-dist
Dynamic: summary
